{
    "info": {
        "name": "Task Management API",
        "description": "Complete API documentation for Task Management System with JWT authentication",
        "schema": "https://schema.getpostman.com/json/collection/v2.1.0/collection.json",
        "_postman_id": "task-management-api-v1",
        "version": "1.0.0"
    },
    "auth": {
        "type": "bearer",
        "bearer": [
            {
                "key": "token",
                "value": "{{jwt_token}}",
                "type": "string"
            }
        ]
    },
    "variable": [
        {
            "key": "base_url",
            "value": "http://localhost:5000",
            "type": "string"
        },
        {
            "key": "jwt_token",
            "value": "",
            "type": "string"
        },
        {
            "key": "task_id",
            "value": "",
            "type": "string"
        },
        {
            "key": "user_id",
            "value": "",
            "type": "string"
        }
    ],
    "item": [
        {
            "name": "Authentication",
            "item": [
                {
                    "name": "Register User",
                    "event": [
                        {
                            "listen": "test",
                            "script": {
                                "exec": [
                                    "if (pm.response.code === 201) {",
                                    "    const response = pm.response.json();",
                                    "    pm.environment.set('jwt_token', response.data.token);",
                                    "    pm.environment.set('user_id', response.data.user.id);",
                                    "}"
                                ]
                            }
                        }
                    ],
                    "request": {
                        "method": "POST",
                        "header": [
                            {
                                "key": "Content-Type",
                                "value": "application/json"
                            }
                        ],
                        "body": {
                            "mode": "raw",
                            "raw": "{\n  \"name\": \"Test User\",\n  \"email\": \"test_unique_{{$timestamp}}@example.com\",\n  \"password\": \"password123\",\n  \"role\": \"user\"\n}"
                        },
                        "url": {
                            "raw": "{{base_url}}/api/auth/register",
                            "host": [
                                "{{base_url}}"
                            ],
                            "path": [
                                "api",
                                "auth",
                                "register"
                            ]
                        },
                        "description": "Register a new user."
                    }
                },
                {
                    "name": "Login",
                    "event": [
                        {
                            "listen": "test",
                            "script": {
                                "exec": [
                                    "if (pm.response.code === 200) {",
                                    "    const response = pm.response.json();",
                                    "    pm.environment.set('jwt_token', response.data.token);",
                                    "    pm.environment.set('user_id', response.data.user.id);",
                                    "}"
                                ]
                            }
                        }
                    ],
                    "request": {
                        "method": "POST",
                        "header": [
                            {
                                "key": "Content-Type",
                                "value": "application/json"
                            }
                        ],
                        "body": {
                            "mode": "raw",
                            "raw": "{\n  \"email\": \"admin@taskmanager.com\",\n  \"password\": \"admin123\"\n}"
                        },
                        "url": {
                            "raw": "{{base_url}}/api/auth/login",
                            "host": [
                                "{{base_url}}"
                            ],
                            "path": [
                                "api",
                                "auth",
                                "login"
                            ]
                        },
                        "description": "Login to receive JWT token."
                    }
                },
                {
                    "name": "Get Current User",
                    "request": {
                        "method": "GET",
                        "header": [],
                        "url": {
                            "raw": "{{base_url}}/api/auth/me",
                            "host": [
                                "{{base_url}}"
                            ],
                            "path": [
                                "api",
                                "auth",
                                "me"
                            ]
                        }
                    }
                }
            ]
        },
        {
            "name": "Tasks",
            "item": [
                {
                    "name": "Create Task",
                    "event": [
                        {
                            "listen": "test",
                            "script": {
                                "exec": [
                                    "if (pm.response.code === 201) {",
                                    "    const response = pm.response.json();",
                                    "    pm.environment.set('task_id', response.data.id);",
                                    "}"
                                ]
                            }
                        }
                    ],
                    "request": {
                        "method": "POST",
                        "header": [
                            {
                                "key": "Content-Type",
                                "value": "application/json"
                            }
                        ],
                        "body": {
                            "mode": "raw",
                            "raw": "{\n  \"title\": \"New Feature Implementation\",\n  \"description\": \"Implement the new feature\",\n  \"status\": \"pending\"\n}"
                        },
                        "url": {
                            "raw": "{{base_url}}/api/tasks",
                            "host": [
                                "{{base_url}}"
                            ],
                            "path": [
                                "api",
                                "tasks"
                            ]
                        },
                        "description": "Create a new task. ID is captured for subsequent requests."
                    }
                },
                {
                    "name": "Get All Tasks",
                    "request": {
                        "method": "GET",
                        "header": [],
                        "url": {
                            "raw": "{{base_url}}/api/tasks",
                            "host": [
                                "{{base_url}}"
                            ],
                            "path": [
                                "api",
                                "tasks"
                            ]
                        }
                    }
                },
                {
                    "name": "Get Single Task",
                    "request": {
                        "method": "GET",
                        "header": [],
                        "url": {
                            "raw": "{{base_url}}/api/tasks/{{task_id}}",
                            "host": [
                                "{{base_url}}"
                            ],
                            "path": [
                                "api",
                                "tasks",
                                "{{task_id}}"
                            ]
                        }
                    }
                },
                {
                    "name": "Update Task",
                    "request": {
                        "method": "PUT",
                        "header": [
                            {
                                "key": "Content-Type",
                                "value": "application/json"
                            }
                        ],
                        "body": {
                            "mode": "raw",
                            "raw": "{\n  \"title\": \"Updated Task Title\",\n  \"status\": \"in_progress\"\n}"
                        },
                        "url": {
                            "raw": "{{base_url}}/api/tasks/{{task_id}}",
                            "host": [
                                "{{base_url}}"
                            ],
                            "path": [
                                "api",
                                "tasks",
                                "{{task_id}}"
                            ]
                        }
                    }
                },
                {
                    "name": "Delete Task",
                    "request": {
                        "method": "DELETE",
                        "header": [],
                        "url": {
                            "raw": "{{base_url}}/api/tasks/{{task_id}}",
                            "host": [
                                "{{base_url}}"
                            ],
                            "path": [
                                "api",
                                "tasks",
                                "{{task_id}}"
                            ]
                        }
                    }
                }
            ]
        },
        {
            "name": "Users (Admin Only)",
            "item": [
                {
                    "name": "Get All Users",
                    "request": {
                        "method": "GET",
                        "header": [],
                        "url": {
                            "raw": "{{base_url}}/api/users",
                            "host": [
                                "{{base_url}}"
                            ],
                            "path": [
                                "api",
                                "users"
                            ]
                        }
                    }
                },
                {
                    "name": "Get Single User",
                    "request": {
                        "method": "GET",
                        "header": [],
                        "url": {
                            "raw": "{{base_url}}/api/users/{{user_id}}",
                            "host": [
                                "{{base_url}}"
                            ],
                            "path": [
                                "api",
                                "users",
                                "{{user_id}}"
                            ]
                        }
                    }
                }
            ]
        }
    ]
}